adminA/__init__.py
adminA/example.py
adminA/models.py
adminA/serializers.py
adminA/urls.py
adminA/views.py
adminA/migrations/0001_initial.py
adminA/migrations/__init__.py
adminA/static/adminA/asset-manifest.json
adminA/static/adminA/index.html
adminA/static/adminA/static/css/2.69771427.chunk.css
adminA/static/adminA/static/css/2.69771427.chunk.css.map
adminA/static/adminA/static/css/main.9e1e7881.chunk.css
adminA/static/adminA/static/css/main.9e1e7881.chunk.css.map
adminA/static/adminA/static/js/2.3d52d79e.chunk.js
adminA/static/adminA/static/js/2.3d52d79e.chunk.js.LICENSE.txt
adminA/static/adminA/static/js/2.3d52d79e.chunk.js.map
adminA/static/adminA/static/js/main.bf87dd4c.chunk.js
adminA/static/adminA/static/js/main.bf87dd4c.chunk.js.map
adminA/static/adminA/static/js/runtime-main.b241f7dd.js
adminA/static/adminA/static/js/runtime-main.b241f7dd.js.map
adminA/static/adminA/static/media/1.a257951a.jpeg
adminA/static/adminA/static/media/1.eaa42e50.jpeg
adminA/static/adminA/static/media/help.2e8c0a40.png
adminA-2024.6.29.17.dist-info/LICENSE
adminA-2024.6.29.17.dist-info/METADATA
adminA-2024.6.29.17.dist-info/WHEEL
adminA-2024.6.29.17.dist-info/top_level.txt
adminA-2024.6.29.17.dist-info/RECORD
