Metadata-Version: 2.1
Name: adminA
Version: 2024.6.29.17
Summary: 为django应用提供快速的管理员页面构建.使用drf及0代码操作提供更快捷的admin页面构建.
Author-email: YanChengxin <yan.cheng.xin@foxmail.com>
Project-URL: Homepage, https://github.com/pypa/sampleproject
Project-URL: Issues, https://github.com/pypa/sampleproject/issues
Classifier: Programming Language :: Python :: 3
Classifier: License :: OSI Approved :: MIT License
Classifier: Operating System :: OS Independent
Requires-Python: >=3.8
License-File: LICENSE
